proxyjudge/__init__.py
proxyjudge/proxyjudge.py
PPTJudge-0.0.1.dist-info/LICENSE
PPTJudge-0.0.1.dist-info/METADATA
PPTJudge-0.0.1.dist-info/WHEEL
PPTJudge-0.0.1.dist-info/entry_points.txt
PPTJudge-0.0.1.dist-info/top_level.txt
PPTJudge-0.0.1.dist-info/RECORD
